youtrack_lap/__init__.py
youtrack_lap/connection.py
youtrack_lap/issueCollection.py
youtrack_lap/issueResource.py
youtrack_lap/projectCollection.py
youtrack_lap/projectResource.py
youtrack_lap-1.0.0.dist-info/METADATA
youtrack_lap-1.0.0.dist-info/WHEEL
youtrack_lap-1.0.0.dist-info/RECORD
