Metadata-Version: 2.4
Name: youtrack-lap
Version: 1.0.0
Summary: A very limited client library for accessing YouTrack REST API
Author-email: Paolo Latella <paolo.latella@recube.it>
License: MIT
Requires-Python: >=3.8
Requires-Dist: httpx>=0.24.0
Requires-Dist: requests>=2.25.0
Provides-Extra: dev
Requires-Dist: black>=22.0; extra == 'dev'
Requires-Dist: flake8>=4.0; extra == 'dev'
Requires-Dist: pytest>=7.0; extra == 'dev'
